iblutil/__init__.py
iblutil/numerical.py
iblutil/random.py
iblutil/spacer.py
iblutil/util.py
iblutil/io/__init__.py
iblutil/io/binary.py
iblutil/io/hashfile.py
iblutil/io/jsonable.py
iblutil/io/params.py
iblutil/io/parquet.py
iblutil/io/net/__init__.py
iblutil/io/net/app.py
iblutil/io/net/base.py
iblutil-1.19.1.dist-info/licenses/LICENSE
iblutil-1.19.1.dist-info/METADATA
iblutil-1.19.1.dist-info/WHEEL
iblutil-1.19.1.dist-info/top_level.txt
iblutil-1.19.1.dist-info/RECORD
