Metadata-Version: 2.4
Name: iblutil
Version: 1.19.1
Summary: Utillity functions and classes for IBL data analysis with minimal dependencies
Author: IBL Staff
License: MIT
Project-URL: Homepage, https://github.com/int-brain-lab/iblutil
Project-URL: Documentation, https://github.com/int-brain-lab/iblutil
Project-URL: Repository, https://github.com/int-brain-lab/iblutil
Project-URL: Issues, https://github.com/int-brain-lab/iblutil/issues
Project-URL: Changelog, https://github.com/int-brain-lab/iblutil/blob/main/CHANGELOG.md
Requires-Python: >=3.10
License-File: LICENSE
Requires-Dist: colorlog>=6.0.0
Requires-Dist: numba
Requires-Dist: numpy>=1.18
Requires-Dist: pandas>=0.24.2
Requires-Dist: pyarrow
Requires-Dist: tqdm>=4.32.1
Requires-Dist: packaging
Requires-Dist: scipy
Dynamic: license-file
